{"web":{"auth_uri":"https://accounts.google.com/o/oauth2/auth","client_secret":"fyUNs6d3G3kg9Cg7FDPYnhkF","token_uri":"https://accounts.google.com/o/oauth2/token","client_email":"506019065654-j3qvmgq0pqaaa8vhqt0filnl26h53dkq@developer.gserviceaccount.com","redirect_uris":["http://teamflyte-affinitymapper.appspot.com/oauth2callback"],"client_x509_cert_url":"https://www.googleapis.com/robot/v1/metadata/x509/506019065654-j3qvmgq0pqaaa8vhqt0filnl26h53dkq@developer.gserviceaccount.com","client_id":"506019065654-j3qvmgq0pqaaa8vhqt0filnl26h53dkq.apps.googleusercontent.com","auth_provider_x509_cert_url":"https://www.googleapis.com/oauth2/v1/certs","javascript_origins":["http://teamflyte-affinitymapper.appspot.com"]}}